fakedns/__init__.py
fakedns/docopt.py
fakedns/fakedns_cli.py
fakedns/fakedns_config_cli.py
fakedns/config/__init__.py
fakedns/config/add_pattern_interactively.py
fakedns/config/configuration.py
fakedns/config/default_config.config
fakedns/config/domain_pattern.py
fakedns/library/__init__.py
fakedns/library/baseline_creation_server.py
fakedns/library/fake_dns_server.py
fakedns-1.2.dist-info/LICENSE
fakedns-1.2.dist-info/METADATA
fakedns-1.2.dist-info/WHEEL
fakedns-1.2.dist-info/entry_points.txt
fakedns-1.2.dist-info/top_level.txt
fakedns-1.2.dist-info/RECORD
