Metadata-Version: 2.1
Name: fakedns
Version: 1.2
Summary: A fake DNS server for malware analysis written in Python3
Home-page: https://github.com/wahlflo/fakedns
Author: Florian Wahl
Author-email: florian.wahl.developer@gmail.com
Classifier: Programming Language :: Python :: 3
Classifier: License :: OSI Approved :: MIT License
Classifier: Operating System :: OS Independent
License-File: LICENSE
Requires-Dist: cli-formatter (>=1.2.0)
Requires-Dist: dns-messages (>=1.0.0)
